mcp_server_mysql/__init__.py
mcp_server_mysql/__main__.py
mcp_server_mysql/py.typed
mcp_server_mysql/server.py
mcp_server_mysql-0.1.4.dist-info/METADATA
mcp_server_mysql-0.1.4.dist-info/WHEEL
mcp_server_mysql-0.1.4.dist-info/entry_points.txt
mcp_server_mysql-0.1.4.dist-info/RECORD
