Metadata-Version: 2.4
Name: mcp-server-mysql
Version: 0.1.4
Summary: Add your description here
Author-email: truskovskiyk <truskovskiyk@gmail.com>
Requires-Python: >=3.12
Requires-Dist: kubernetes>=32.0.1
Requires-Dist: mcp[cli]>=1.4.1
Requires-Dist: mysql-connector-python>=9.2.0
Requires-Dist: pydantic-settings>=2.8.1
